exifmgr/__init__.py
exifmgr/runner.py
exifmgr/skeleton.py
exifmgr-0.0.3.dist-info/LICENSE.txt
exifmgr-0.0.3.dist-info/METADATA
exifmgr-0.0.3.dist-info/WHEEL
exifmgr-0.0.3.dist-info/entry_points.txt
exifmgr-0.0.3.dist-info/top_level.txt
exifmgr-0.0.3.dist-info/RECORD
