Metadata-Version: 2.1
Name: exifmgr
Version: 0.0.3
Summary: Photo organizer / wrapper for Exiftool
Home-page: https://github.com/bluszcz/exifmgr
Author: Rafał Zawadzki
Author-email: bluszcz@bluszcz.net
License: MIT
Project-URL: Documentation, https://github.com/bluszcz/exifmgr
Platform: any
Classifier: Development Status :: 4 - Beta
Classifier: Programming Language :: Python
License-File: LICENSE.txt
Requires-Dist: progressbar2
Requires-Dist: importlib-metadata ; python_version < "3.8"
Provides-Extra: testing
Requires-Dist: setuptools ; extra == 'testing'
Requires-Dist: pytest ; extra == 'testing'
Requires-Dist: pytest-cov ; extra == 'testing'
